svmbolcore/__init__.py
svmbolcore/codegen/__init__.py
svmbolcore/codegen/basics.py
svmbolcore/codegen/parse.py
svmbolcore/core/__init__.py
svmbolcore/core/calculus.py
svmbolcore/core/solve.py
svmbolcore/core/symbol.py
svmbolcore-0.2.dist-info/METADATA
svmbolcore-0.2.dist-info/WHEEL
svmbolcore-0.2.dist-info/top_level.txt
svmbolcore-0.2.dist-info/RECORD
