Metadata-Version: 2.4
Name: svmbolcore
Version: 0.2
Summary: symbolic math lib that generates parallel CUDA
Home-page: https://github.com/yourusername/svmbolcore
Author: codespaceDrifter
Author-email: codespaceDrifter@gmail.com
Classifier: Programming Language :: Python :: 3
Classifier: License :: OSI Approved :: MIT License
Classifier: Operating System :: OS Independent
Requires-Python: >=3.7
Dynamic: author
Dynamic: author-email
Dynamic: classifier
Dynamic: description
Dynamic: description-content-type
Dynamic: home-page
Dynamic: requires-python
Dynamic: summary
